AnnotationPipeline-0.18.data/scripts/annotation_pipeline
AnnotationPipeline-0.18.data/scripts/fastaSplitter
AnnotationPipeline-0.18.dist-info/METADATA
AnnotationPipeline-0.18.dist-info/RECORD
AnnotationPipeline-0.18.dist-info/WHEEL
AnnotationPipeline-0.18.dist-info/top_level.txt
rnaseqpipeline/Blast.py
rnaseqpipeline/Install.py
rnaseqpipeline/Run.py
rnaseqpipeline/__init__.py
