Metadata-Version: 2.1
Name: AnnotationPipeline
Version: 0.18
Summary: WUR nematology Annotation Pipeline
Home-page: UNKNOWN
Author: Joris van Steenbrugge
Author-email: joris.vansteenbrugge@wur.nl
License: UNKNOWN
Platform: UNKNOWN
Requires-Dist: joblib
Requires-Dist: biopython
